Workbook

Sheet Sheet1
A2: Three Statement Operating Model: Nike
R3: Year over Year Growth
H4: Actual or Forecast | I4: Actual | J4: Actual | K4: Actual | L4: Forecast | M4: Forecast | N4: Forecast | O4: Forecast | P4: Forecast | R4: =K4 -> Actual | S4: {=L4:P4} -> Forecast | T4: Forecast | U4: Forecast | V4: Forecast | W4: Forecast
A5: Master Error Check Cell | B5: ='Control Panel'!B4 -> 0 | H5: Year | I5: {=_xlfn.SEQUENCE(,8,"2022")} -> 2022 | J5: 2023 | K5: 2024 | L5: 2025 | M5: 2026 | N5: 2027 | O5: 2028 | P5: 2029 | R5: 2024 | S5: 2025 | T5: 2026 | U5: 2027 | V5: 2028 | W5: 2029
A6: Item (in millions) | B6: Assumptions | F6: Notes
A7: Income Statement
A8: Revenues | B8: Stepped Assumption: see note | F8: See note in Assumptions section | I8: 46710 | J8: 51217 | K8: 51362 | L8: =K8*(1+0.5%) -> 51618.81 | M8: =L8*(1+2%) -> 52651.186 | N8: =M8*(1+4%) -> 54757.234 | O8: =N8*(1+5%) -> 57495.095 | P8: =O8*(1+6%) -> 60944.801 | R8: =IFERROR((K8/J8)-1,0) -> 0.0028310912 | S8: =IFERROR((L8/K8)-1,0) -> 0.005 | T8: =IFERROR((M8/L8)-1,0) -> 0.02 | U8: =IFERROR((N8/M8)-1,0) -> 0.04 | V8: =IFERROR((O8/N8)-1,0) -> 0.05 | W8: =IFERROR((P8/O8)-1,0) -> 0.06
A9: Cost of Goods Sold | F9: Revenue - Gross Profit | I9: 25231 | J9: 28925 | K9: 28475 | L9: =L8-L10 -> 29422.722 | M9: =M8-M10 -> 30011.176 | N9: =N8-N10 -> 31211.623 | O9: =O8-O10 -> 32772.204 | P9: =P8-P10 -> 34738.537 | R9: =IFERROR((K9/J9)-1,0) -> -0.015557476 | S9: =IFERROR((L9/K9)-1,0) -> 0.033282588 | T9: =IFERROR((M9/L9)-1,0) -> 0.02 | U9: =IFERROR((N9/M9)-1,0) -> 0.04 | V9: =IFERROR((O9/N9)-1,0) -> 0.05 | W9: =IFERROR((P9/O9)-1,0) -> 0.06
A10: Gross profit | F10: Revenue * Gross Maargin | I10: 21479 | J10: 22292 | K10: 22887 | L10: =L8*L11 -> 22196.088 | M10: =M8*M11 -> 22640.01 | N10: =N8*N11 -> 23545.61 | O10: =O8*O11 -> 24722.891 | P10: =P8*P11 -> 26206.264 | R10: =IFERROR((K10/J10)-1,0) -> 0.02669119 | S10: =IFERROR((L10/K10)-1,0) -> -0.030187954 | T10: =IFERROR((M10/L10)-1,0) -> 0.02 | U10: =IFERROR((N10/M10)-1,0) -> 0.04 | V10: =IFERROR((O10/N10)-1,0) -> 0.05 | W10: =IFERROR((P10/O10)-1,0) -> 0.06
A11: Gross Margin | B11: 0.43 | I11: =I10/I8 -> 0.45983729 | J11: =J10/J8 -> 0.43524611 | K11: =K10/K8 -> 0.44560181 | L11: =$B$11 -> 0.43 | M11: =$B$11 -> 0.43 | N11: =$B$11 -> 0.43 | O11: =$B$11 -> 0.43 | P11: =$B$11 -> 0.43
A13: SG&A Expenses | B13: 0.26 | F13: 26% of Total SG&A
A14: Demand creation expense | B14: 0.74 | F14: 74% of Total SG&A | I14: 3850 | J14: 4060 | K14: 4285 | L14: =L16*$B$13 -> 4253.5402 | M14: =M16*$B$13 -> 4338.611 | N14: =N16*$B$13 -> 4512.1555 | O14: =O16*$B$13 -> 4737.7633 | P14: =P16*$B$13 -> 5022.0291 | R14: =IFERROR((K14/J14)-1,0) -> 0.055418719 | S14: =IFERROR((L14/K14)-1,0) -> -0.0073418351 | T14: =IFERROR((M14/L14)-1,0) -> 0.02 | U14: =IFERROR((N14/M14)-1,0) -> 0.04 | V14: =IFERROR((O14/N14)-1,0) -> 0.05 | W14: =IFERROR((P14/O14)-1,0) -> 0.06
A15: Operating overhead expense | I15: 10954 | J15: 12317 | K15: 12291 | L15: =L16*$B$14 -> 12106.23 | M15: =M16*$B$14 -> 12348.355 | N15: =N16*$B$14 -> 12842.289 | O15: =O16*$B$14 -> 13484.403 | P15: =P16*$B$14 -> 14293.467 | R15: =IFERROR((K15/J15)-1,0) -> -0.0021109036 | S15: =IFERROR((L15/K15)-1,0) -> -0.015032959 | T15: =IFERROR((M15/L15)-1,0) -> 0.02 | U15: =IFERROR((N15/M15)-1,0) -> 0.04 | V15: =IFERROR((O15/N15)-1,0) -> 0.05 | W15: =IFERROR((P15/O15)-1,0) -> 0.06
A16: Total selling and administrative expense | B16: =I16/I8 -> 0.31693428 | F16: Revenue * Assumption | I16: 14804 | J16: 16377 | K16: 16576 | L16: =L8*$B$16 -> 16359.77 | M16: =M8*$B$16 -> 16686.966 | N16: =N8*$B$16 -> 17354.444 | O16: =O8*$B$16 -> 18222.166 | P16: =P8*$B$16 -> 19315.496 | R16: =IFERROR((K16/J16)-1,0) -> 0.012151188 | S16: =IFERROR((L16/K16)-1,0) -> -0.013044755 | T16: =IFERROR((M16/L16)-1,0) -> 0.02 | U16: =IFERROR((N16/M16)-1,0) -> 0.04 | V16: =IFERROR((O16/N16)-1,0) -> 0.05 | W16: =IFERROR((P16/O16)-1,0) -> 0.06
A18: EBIT (Operating Income) | I18: =I10-I16 -> 6675 | J18: =J10-J16 -> 5915 | K18: =K10-K16 -> 6311 | L18: =L10-L16 -> 5836.3182 | M18: =M10-M16 -> 5953.0445 | N18: =N10-N16 -> 6191.1663 | O18: =O10-O16 -> 6500.7246 | P18: =P10-P16 -> 6890.7681 | R18: =IFERROR((K18/J18)-1,0) -> 0.066948436 | S18: =IFERROR((L18/K18)-1,0) -> -0.075214996 | T18: =IFERROR((M18/L18)-1,0) -> 0.02 | U18: =IFERROR((N18/M18)-1,0) -> 0.04 | V18: =IFERROR((O18/N18)-1,0) -> 0.05 | W18: =IFERROR((P18/O18)-1,0) -> 0.06
A19: Interest | I19: 205 | J19: -6 | K19: -161 | L19: -161 | M19: -161 | N19: -161 | O19: -161 | P19: -161 | R19: =IFERROR((K19/J19)-1,0) -> 25.833333 | S19: =IFERROR((L19/K19)-1,0) -> 0 | T19: =IFERROR((M19/L19)-1,0) -> 0 | U19: =IFERROR((N19/M19)-1,0) -> 0 | V19: =IFERROR((O19/N19)-1,0) -> 0 | W19: =IFERROR((P19/O19)-1,0) -> 0
A20: Other (income) expense, net | I20: -181 | J20: -280 | K20: -228 | L20: -228 | M20: -228 | N20: -228 | O20: -228 | P20: -228 | R20: =IFERROR((K20/J20)-1,0) -> -0.18571429 | S20: =IFERROR((L20/K20)-1,0) -> 0 | T20: =IFERROR((M20/L20)-1,0) -> 0 | U20: =IFERROR((N20/M20)-1,0) -> 0 | V20: =IFERROR((O20/N20)-1,0) -> 0 | W20: =IFERROR((P20/O20)-1,0) -> 0
A21: Income before income taxes | I21: =I18-I19-I20 -> 6651 | J21: =J18-J19-J20 -> 6201 | K21: =K18-K19-K20 -> 6700 | L21: =L18-L19-L20 -> 6225.3182 | M21: =M18-M19-M20 -> 6342.0445 | N21: =N18-N19-N20 -> 6580.1663 | O21: =O18-O19-O20 -> 6889.7246 | P21: =P18-P19-P20 -> 7279.7681 | R21: =IFERROR((K21/J21)-1,0) -> 0.080470892 | S21: =IFERROR((L21/K21)-1,0) -> -0.070848036 | T21: =IFERROR((M21/L21)-1,0) -> 0.018750265 | U21: =IFERROR((N21/M21)-1,0) -> 0.037546533 | V21: =IFERROR((O21/N21)-1,0) -> 0.047044148 | W21: =IFERROR((P21/O21)-1,0) -> 0.056612346
A22: Income tax expense | B22: 0.15 | F22: Percent of Operating Income | I22: 605 | J22: 1131 | K22: 1000 | L22: =L21*$B$22 -> 933.79772 | M22: =M21*$B$22 -> 951.30668 | N22: =N21*$B$22 -> 987.02495 | O22: =O21*$B$22 -> 1033.4587 | P22: =P21*$B$22 -> 1091.9652 | R22: =IFERROR((K22/J22)-1,0) -> -0.1158267 | S22: =IFERROR((L22/K22)-1,0) -> -0.066202276 | T22: =IFERROR((M22/L22)-1,0) -> 0.018750265 | U22: =IFERROR((N22/M22)-1,0) -> 0.037546533 | V22: =IFERROR((O22/N22)-1,0) -> 0.047044148 | W22: =IFERROR((P22/O22)-1,0) -> 0.056612346
A23: Net income | I23: 6046 | J23: 5070 | K23: 5700 | L23: =L21-L22 -> 5291.5204 | M23: =M21-M22 -> 5390.7378 | N23: =N21-N22 -> 5593.1414 | O23: =O21-O22 -> 5856.2659 | P23: =P21-P22 -> 6187.8029 | R23: =IFERROR((K23/J23)-1,0) -> 0.12426036 | S23: =IFERROR((L23/K23)-1,0) -> -0.071663081 | T23: =IFERROR((M23/L23)-1,0) -> 0.018750265 | U23: =IFERROR((N23/M23)-1,0) -> 0.037546533 | V23: =IFERROR((O23/N23)-1,0) -> 0.047044148 | W23: =IFERROR((P23/O23)-1,0) -> 0.056612346
A24: Margin | I24: =I23/I8 -> 0.12943695 | J24: =J23/J8 -> 0.09899057 | K24: =K23/K8 -> 0.11097699 | L24: =L23/L8 -> 0.10251148 | M24: =M23/M8 -> 0.10238588 | N24: =N23/N8 -> 0.10214434 | O24: =O23/O8 -> 0.10185679 | P24: =P23/P8 -> 0.10153127
A26: EBITDA, as Defined
A27: Net Income | I27: {=I23:K23} -> 6046 | J27: 5070 | K27: 5700 | L27: =L23 -> 5291.5204 | M27: =M23 -> 5390.7378 | N27: =N23 -> 5593.1414 | O27: =O23 -> 5856.2659 | P27: =P23 -> 6187.8029 | R27: =IFERROR((K27/J27)-1,0) -> 0.12426036 | S27: =IFERROR((L27/K27)-1,0) -> -0.071663081 | T27: =IFERROR((M27/L27)-1,0) -> 0.018750265 | U27: =IFERROR((N27/M27)-1,0) -> 0.037546533 | V27: =IFERROR((O27/N27)-1,0) -> 0.047044148 | W27: =IFERROR((P27/O27)-1,0) -> 0.056612346
A28: Interest | I28: 205 | J28: -6 | K28: -161 | L28: =L19 -> -161 | M28: =M19 -> -161 | N28: =N19 -> -161 | O28: =O19 -> -161 | P28: =P19 -> -161 | R28: =IFERROR((K28/J28)-1,0) -> 25.833333 | S28: =IFERROR((L28/K28)-1,0) -> 0 | T28: =IFERROR((M28/L28)-1,0) -> 0 | U28: =IFERROR((N28/M28)-1,0) -> 0 | V28: =IFERROR((O28/N28)-1,0) -> 0 | W28: =IFERROR((P28/O28)-1,0) -> 0
A29: Income tax expense | I29: 605 | J29: 1131 | K29: 1000 | L29: =L22 -> 933.79772 | M29: =M22 -> 951.30668 | N29: =N22 -> 987.02495 | O29: =O22 -> 1033.4587 | P29: =P22 -> 1091.9652 | R29: =IFERROR((K29/J29)-1,0) -> -0.1158267 | S29: =IFERROR((L29/K29)-1,0) -> -0.066202276 | T29: =IFERROR((M29/L29)-1,0) -> 0.018750265 | U29: =IFERROR((N29/M29)-1,0) -> 0.037546533 | V29: =IFERROR((O29/N29)-1,0) -> 0.047044148 | W29: =IFERROR((P29/O29)-1,0) -> 0.056612346
A30: Depreciation | I30: 717 | J30: 703 | K30: 796 | L30: =L177 -> 856.42857 | M30: =M177 -> 916.85714 | N30: =N177 -> 977.28571 | O30: =O177 -> 1037.7143 | P30: =P177 -> 1098.1429 | R30: =IFERROR((K30/J30)-1,0) -> 0.13229018 | S30: =IFERROR((L30/K30)-1,0) -> 0.075915291 | T30: =IFERROR((M30/L30)-1,0) -> 0.070558799 | U30: =IFERROR((N30/M30)-1,0) -> 0.065908383 | V30: =IFERROR((O30/N30)-1,0) -> 0.061833065 | W30: =IFERROR((P30/O30)-1,0) -> 0.058232379
A31: Amortization | I31: 123 | J31: 156 | K31: 48 | L31: 48 | M31: 48 | N31: 48 | O31: 48 | P31: 48
A32: Toal EBITDA Adjustments | I32: =SUM(I28:I31) -> 1650 | J32: =SUM(J28:J31) -> 1984 | K32: =SUM(K28:K31) -> 1683 | L32: =SUM(L28:L31) -> 1677.2263 | M32: =SUM(M28:M31) -> 1755.1638 | N32: =SUM(N28:N31) -> 1851.3107 | O32: =SUM(O28:O31) -> 1958.173 | P32: =SUM(P28:P31) -> 2077.1081 | R32: =IFERROR((K32/J32)-1,0) -> -0.15171371 | S32: =IFERROR((L32/K32)-1,0) -> -0.0034306028 | T32: =IFERROR((M32/L32)-1,0) -> 0.046468104 | U32: =IFERROR((N32/M32)-1,0) -> 0.05477941 | V32: =IFERROR((O32/N32)-1,0) -> 0.057722521 | W32: =IFERROR((P32/O32)-1,0) -> 0.060737787
A33: EBITDA, as Defined | I33: =I27+I32 -> 7696 | J33: =J27+J32 -> 7054 | K33: =K27+K32 -> 7383 | L33: =L27+L32 -> 6968.7467 | M33: =M27+M32 -> 7145.9017 | N33: =N27+N32 -> 7444.452 | O33: =O27+O32 -> 7814.4389 | P33: =P28+P32 -> 1916.1081 | R33: =IFERROR((K33/J33)-1,0) -> 0.046640204 | S33: =IFERROR((L33/K33)-1,0) -> -0.056109071 | T33: =IFERROR((M33/L33)-1,0) -> 0.025421348 | U33: =IFERROR((N33/M33)-1,0) -> 0.041779242 | V33: =IFERROR((O33/N33)-1,0) -> 0.04969968 | W33: =IFERROR((P33/O33)-1,0) -> -0.75479902
A34: Margin | I34: =I33/I9 -> 0.3050216 | J34: =J33/J9 -> 0.24387208 | K34: =K33/K9 -> 0.25928007 | L34: =L33/L9 -> 0.23684915 | M34: =M33/M9 -> 0.23810802 | N34: =N33/N9 -> 0.23851538 | O34: =O33/O9 -> 0.23844716 | P34: =P33/P9 -> 0.055157996
A36: Balance Sheet
A37: Assets
A38: Current Assets:
A39: Cash and equivalents | I39: 8574 | J39: 7441 | K39: 9860 | L39: {=L127:P127} -> 10296.25 | M39: 10555.851 | N39: 10831.81 | O39: 11286.283 | P39: 12969.308 | R39: =IFERROR((K39/J39)-1,0) -> 0.32509071 | S39: =IFERROR((L39/K39)-1,0) -> 0.044244435 | T39: =IFERROR((M39/L39)-1,0) -> 0.025213161 | U39: =IFERROR((N39/M39)-1,0) -> 0.026142786 | V39: =IFERROR((O39/N39)-1,0) -> 0.041957176 | W39: =IFERROR((P39/O39)-1,0) -> 0.14912134
A40: Short-term investments | F40: Held Flat for Forecast | I40: 4423 | J40: 3234 | K40: 1722 | L40: 1722 | M40: 1722 | N40: 1722 | O40: 1722 | P40: 1722 | R40: =IFERROR((K40/J40)-1,0) -> -0.46753247 | S40: =IFERROR((L40/K40)-1,0) -> 0 | T40: =IFERROR((M40/L40)-1,0) -> 0 | U40: =IFERROR((N40/M40)-1,0) -> 0 | V40: =IFERROR((O40/N40)-1,0) -> 0 | W40: =IFERROR((P40/O40)-1,0) -> 0
A41: Accounts receivable, net | F41: See Networking Capital Schedule | I41: 4667 | J41: 4131 | K41: 4427 | L41: =L134 -> 4384.0633 | M41: =M134 -> 4471.7446 | N41: =N134 -> 4650.6144 | O41: =O134 -> 4883.1451 | P41: =P134 -> 5176.1338 | R41: =IFERROR((K41/J41)-1,0) -> 0.071653353 | S41: =IFERROR((L41/K41)-1,0) -> -0.009698822 | T41: =IFERROR((M41/L41)-1,0) -> 0.02 | U41: =IFERROR((N41/M41)-1,0) -> 0.04 | V41: =IFERROR((O41/N41)-1,0) -> 0.05 | W41: =IFERROR((P41/O41)-1,0) -> 0.06
A42: Inventories | F42: See Networking Capital Schedule | I42: 8420 | J42: 8454 | K42: 7519 | L42: =L135 -> 8423.7655 | M42: =M135 -> 8592.2408 | N42: =N135 -> 8935.9305 | O42: =O135 -> 9382.727 | P42: =P135 -> 9945.6906 | R42: =IFERROR((K42/J42)-1,0) -> -0.11059853 | S42: =IFERROR((L42/K42)-1,0) -> 0.12033057 | T42: =IFERROR((M42/L42)-1,0) -> 0.02 | U42: =IFERROR((N42/M42)-1,0) -> 0.04 | V42: =IFERROR((O42/N42)-1,0) -> 0.05 | W42: =IFERROR((P42/O42)-1,0) -> 0.06
A43: Prepaid expenses and other current assets | F43: See Networking Capital Schedule | I43: 2129 | J43: 1942 | K43: 1854 | L43: =L136 -> 2064.7524 | M43: =M136 -> 2106.0474 | N43: =N136 -> 2190.2893 | O43: =O136 -> 2299.8038 | P43: =P136 -> 2437.792 | R43: =IFERROR((K43/J43)-1,0) -> -0.045314109 | S43: =IFERROR((L43/K43)-1,0) -> 0.11367443 | T43: =IFERROR((M43/L43)-1,0) -> 0.02 | U43: =IFERROR((N43/M43)-1,0) -> 0.04 | V43: =IFERROR((O43/N43)-1,0) -> 0.05 | W43: =IFERROR((P43/O43)-1,0) -> 0.06
A45: Total current assets | I45: 28213 | J45: 25202 | K45: 25382 | L45: =SUM(L39:L44) -> 26890.831 | M45: =SUM(M39:M44) -> 27447.884 | N45: =SUM(N39:N44) -> 28330.645 | O45: =SUM(O39:O44) -> 29573.959 | P45: =SUM(P39:P44) -> 32250.925 | R45: =IFERROR((K45/J45)-1,0) -> 0.0071422903 | S45: =IFERROR((L45/K45)-1,0) -> 0.059444936 | T45: =IFERROR((M45/L45)-1,0) -> 0.020715337 | U45: =IFERROR((N45/M45)-1,0) -> 0.032161338 | V45: =IFERROR((O45/N45)-1,0) -> 0.043885831 | W45: =IFERROR((P45/O45)-1,0) -> 0.090517682
A47: Long-term assets:
A48: Property, plant and equipment, net | F48: See PP&E Schedule | I48: 4791 | J48: 5081 | K48: 5000 | L48: =L158 -> 4989.5714 | M48: =M158 -> 4918.7143 | N48: =N158 -> 4787.4286 | O48: =O158 -> 4595.7143 | P48: =P158 -> 4343.5714 | R48: =IFERROR((K48/J48)-1,0) -> -0.015941744 | S48: =IFERROR((L48/K48)-1,0) -> -0.0020857143 | T48: =IFERROR((M48/L48)-1,0) -> -0.014201048 | U48: =IFERROR((N48/M48)-1,0) -> -0.026691063 | V48: =IFERROR((O48/N48)-1,0) -> -0.040045357 | W48: =IFERROR((P48/O48)-1,0) -> -0.054864781
A49: Operating lease right-of-use assets, net | B49: 0.01 | F49: 1% growth per year | I49: 2926 | J49: 2923 | K49: 2718 | L49: =K49*(1+$B$49) -> 2745.18 | M49: =L49*(1+$B$49) -> 2772.6318 | N49: =M49*(1+$B$49) -> 2800.3581 | O49: =N49*(1+$B$49) -> 2828.3617 | P49: =O49*(1+$B$49) -> 2856.6453 | R49: =IFERROR((K49/J49)-1,0) -> -0.070133425 | S49: =IFERROR((L49/K49)-1,0) -> 0.01 | T49: =IFERROR((M49/L49)-1,0) -> 0.01 | U49: =IFERROR((N49/M49)-1,0) -> 0.01 | V49: =IFERROR((O49/N49)-1,0) -> 0.01 | W49: =IFERROR((P49/O49)-1,0) -> 0.01
A50: Identifiable intangible assets, net | F50: Prior year - Amortization | I50: 286 | J50: 274 | K50: 259 | L50: =K50-L31 -> 211 | M50: =L50-M31 -> 163 | N50: =M50-N31 -> 115 | O50: =N50-O31 -> 67 | P50: =O50-P31 -> 19 | R50: =IFERROR((K50/J50)-1,0) -> -0.054744526 | S50: =IFERROR((L50/K50)-1,0) -> -0.18532819 | T50: =IFERROR((M50/L50)-1,0) -> -0.22748815 | U50: =IFERROR((N50/M50)-1,0) -> -0.29447853 | V50: =IFERROR((O50/N50)-1,0) -> -0.4173913 | W50: =IFERROR((P50/O50)-1,0) -> -0.71641791
A51: Goodwill | F51: Held Flat for Forecast | I51: 284 | J51: 281 | K51: 240 | L51: 240 | M51: 240 | N51: 240 | O51: 240 | P51: 240 | R51: =IFERROR((K51/J51)-1,0) -> -0.14590747 | S51: =IFERROR((L51/K51)-1,0) -> 0 | T51: =IFERROR((M51/L51)-1,0) -> 0 | U51: =IFERROR((N51/M51)-1,0) -> 0 | V51: =IFERROR((O51/N51)-1,0) -> 0 | W51: =IFERROR((P51/O51)-1,0) -> 0
A52: Deferred income taxes and other assets | F52: Held Flat for Forecast | I52: 3821 | J52: 3770 | K52: 4511 | L52: 4511 | M52: 4511 | N52: 4511 | O52: 4511 | P52: 4511 | R52: =IFERROR((K52/J52)-1,0) -> 0.19655172 | S52: =IFERROR((L52/K52)-1,0) -> 0 | T52: =IFERROR((M52/L52)-1,0) -> 0 | U52: =IFERROR((N52/M52)-1,0) -> 0 | V52: =IFERROR((O52/N52)-1,0) -> 0 | W52: =IFERROR((P52/O52)-1,0) -> 0
A54: Total long-term assets | I54: 12108 | J54: 12329 | K54: 12728 | L54: =SUM(L48:L53) -> 12696.751 | M54: =SUM(M48:M53) -> 12605.346 | N54: =SUM(N48:N53) -> 12453.787 | O54: =SUM(O48:O53) -> 12242.076 | P54: =SUM(P48:P53) -> 11970.217 | R54: =IFERROR((K54/J54)-1,0) -> 0.032362722 | S54: =IFERROR((L54/K54)-1,0) -> -0.0024551046 | T54: =IFERROR((M54/L54)-1,0) -> -0.0071991126 | U54: =IFERROR((N54/M54)-1,0) -> -0.012023422 | V54: =IFERROR((O54/N54)-1,0) -> -0.016999705 | W54: =IFERROR((P54/O54)-1,0) -> -0.022206956
A55: Total Assets | I55: 40321 | J55: 37531 | K55: 38110 | L55: =L45+L54 -> 39587.583 | M55: =M45+M54 -> 40053.23 | N55: =N45+N54 -> 40784.431 | O55: =O45+O54 -> 41816.035 | P55: =P45+P54 -> 44221.141 | R55: =IFERROR((K55/J55)-1,0) -> 0.015427247 | S55: =IFERROR((L55/K55)-1,0) -> 0.038771525 | T55: =IFERROR((M55/L55)-1,0) -> 0.011762458 | U55: =IFERROR((N55/M55)-1,0) -> 0.018255738 | V55: =IFERROR((O55/N55)-1,0) -> 0.025294044 | W55: =IFERROR((P55/O55)-1,0) -> 0.05751638
A57: LIABILITIES AND SHAREHOLDERS' EQUITY
A58: Current liabilities:
A59: Current portion of long-term debt | F59: See Maturity Debt Schedule | I59: 500 | J59: 0 | K59: 1000 | L59: =L196*-1 -> 1000 | M59: =M196*-1 -> 1000 | N59: =N196*-1 -> 1000 | O59: =O196*-1 -> 0 | P59: =P196*-1 -> 0 | R59: =IFERROR((K59/J59)-1,0) -> 0 | S59: =IFERROR((L59/K59)-1,0) -> 0 | T59: =IFERROR((M59/L59)-1,0) -> 0 | U59: =IFERROR((N59/M59)-1,0) -> 0 | V59: =IFERROR((O59/N59)-1,0) -> -1 | W59: =IFERROR((P59/O59)-1,0) -> 0
A60: Notes payable | F60: Held Flat for forecast | I60: 10 | J60: 6 | K60: 6 | L60: 6 | M60: 6 | N60: 6 | O60: 6 | P60: 6 | R60: =IFERROR((K60/J60)-1,0) -> 0 | S60: =IFERROR((L60/K60)-1,0) -> 0 | T60: =IFERROR((M60/L60)-1,0) -> 0 | U60: =IFERROR((N60/M60)-1,0) -> 0 | V60: =IFERROR((O60/N60)-1,0) -> 0 | W60: =IFERROR((P60/O60)-1,0) -> 0
A61: Accounts payable | F61: See Networking Capital Schedule | I61: 3358 | J61: 2862 | K61: 2851 | L61: =L137 -> 3022.8824 | M61: =M137 -> 3083.34 | N61: =N137 -> 3206.6736 | O61: =O137 -> 3367.0073 | P61: =P137 -> 3569.0277 | R61: =IFERROR((K61/J61)-1,0) -> -0.0038434661 | S61: =IFERROR((L61/K61)-1,0) -> 0.060288448 | T61: =IFERROR((M61/L61)-1,0) -> 0.02 | U61: =IFERROR((N61/M61)-1,0) -> 0.04 | V61: =IFERROR((O61/N61)-1,0) -> 0.05 | W61: =IFERROR((P61/O61)-1,0) -> 0.06
A62: Current portion of operating lease liabilities | F62: Held Flat for forecast | I62: 420 | J62: 425 | K62: 477 | L62: 477 | M62: 477 | N62: 477 | O62: 477 | P62: 477 | R62: =IFERROR((K62/J62)-1,0) -> 0.12235294 | S62: =IFERROR((L62/K62)-1,0) -> 0 | T62: =IFERROR((M62/L62)-1,0) -> 0 | U62: =IFERROR((N62/M62)-1,0) -> 0 | V62: =IFERROR((O62/N62)-1,0) -> 0 | W62: =IFERROR((P62/O62)-1,0) -> 0
A63: Accrued liabilities | F63: See Networking Capital Schedule | I63: 6220 | J63: 5723 | K63: 5725 | L63: =L138 -> 6194.2572 | M63: =M138 -> 6318.1423 | N63: =N138 -> 6570.868 | O63: =O138 -> 6899.4114 | P63: =P138 -> 7313.3761 | R63: =IFERROR((K63/J63)-1,0) -> 0.00034946706 | S63: =IFERROR((L63/K63)-1,0) -> 0.081966323 | T63: =IFERROR((M63/L63)-1,0) -> 0.02 | U63: =IFERROR((N63/M63)-1,0) -> 0.04 | V63: =IFERROR((O63/N63)-1,0) -> 0.05 | W63: =IFERROR((P63/O63)-1,0) -> 0.06
A64: Income taxes payable | F64: See Taxes Payable Schedule | I64: 222 | J64: 240 | K64: 534 | L64: {=L150:P150} -> 761.79772 | M64: 1007.1044 | N64: 1288.1293 | O64: 1615.588 | P64: 2001.5533 | R64: =IFERROR((K64/J64)-1,0) -> 1.225 | S64: =IFERROR((L64/K64)-1,0) -> 0.4265875 | T64: =IFERROR((M64/L64)-1,0) -> 0.32201025 | U64: =IFERROR((N64/M64)-1,0) -> 0.27904252 | V64: =IFERROR((O64/N64)-1,0) -> 0.25421259 | W64: =IFERROR((P64/O64)-1,0) -> 0.23890076
A66: Total current liabilities | I66: 10730 | J66: 9256 | K66: 10593 | L66: =SUM(L59:L65) -> 11461.937 | M66: =SUM(M59:M65) -> 11891.587 | N66: =SUM(N59:N65) -> 12548.671 | O66: =SUM(O59:O65) -> 12365.007 | P66: =SUM(P59:P65) -> 13366.957 | R66: =IFERROR((K66/J66)-1,0) -> 0.14444685 | S66: =IFERROR((L66/K66)-1,0) -> 0.082029386 | T66: =IFERROR((M66/L66)-1,0) -> 0.037484891 | U66: =IFERROR((N66/M66)-1,0) -> 0.055256229 | V66: =IFERROR((O66/N66)-1,0) -> -0.014636149 | W66: =IFERROR((P66/O66)-1,0) -> 0.081031119
A68: Long-term liabilities:
A69: Long-term debt | F69: See Term Debt Schedule | I69: 8920 | J69: 8927 | K69: 7903 | L69: =L185 -> 6903 | M69: =M185 -> 5903 | N69: =N185 -> 4903 | O69: =O185 -> 4903 | P69: =P185 -> 4903 | R69: =IFERROR((K69/J69)-1,0) -> -0.11470819 | S69: =IFERROR((L69/K69)-1,0) -> -0.12653423 | T69: =IFERROR((M69/L69)-1,0) -> -0.14486455 | U69: =IFERROR((N69/M69)-1,0) -> -0.16940539 | V69: =IFERROR((O69/N69)-1,0) -> 0 | W69: =IFERROR((P69/O69)-1,0) -> 0
A70: Operating lease liabilities | F70: Held Flat for forecast | I70: 2777 | J70: 2786 | K70: 2566 | L70: 2566 | M70: 2566 | N70: 2566 | O70: 2566 | P70: 2566 | R70: =IFERROR((K70/J70)-1,0) -> -0.07896626 | S70: =IFERROR((L70/K70)-1,0) -> 0 | T70: =IFERROR((M70/L70)-1,0) -> 0 | U70: =IFERROR((N70/M70)-1,0) -> 0 | V70: =IFERROR((O70/N70)-1,0) -> 0 | W70: =IFERROR((P70/O70)-1,0) -> 0
A71: Deferred income taxes and other liabilities | F71: Held Flat for forecast | I71: 2613 | J71: 2558 | K71: 2618 | L71: 2618 | M71: 2618 | N71: 2618 | O71: 2618 | P71: 2618 | R71: =IFERROR((K71/J71)-1,0) -> 0.023455825 | S71: =IFERROR((L71/K71)-1,0) -> 0 | T71: =IFERROR((M71/L71)-1,0) -> 0 | U71: =IFERROR((N71/M71)-1,0) -> 0 | V71: =IFERROR((O71/N71)-1,0) -> 0 | W71: =IFERROR((P71/O71)-1,0) -> 0
A73: Total long-term liabilities | I73: 14310 | J73: 14271 | K73: 13087 | L73: =SUM(L69:L71) -> 12087 | M73: =SUM(M69:M71) -> 11087 | N73: =SUM(N69:N71) -> 10087 | O73: =SUM(O69:O71) -> 10087 | P73: =SUM(P69:P71) -> 10087 | R73: =IFERROR((K73/J73)-1,0) -> -0.082965454 | S73: =IFERROR((L73/K73)-1,0) -> -0.076411706 | T73: =IFERROR((M73/L73)-1,0) -> -0.082733515 | U73: =IFERROR((N73/M73)-1,0) -> -0.090195725 | V73: =IFERROR((O73/N73)-1,0) -> 0 | W73: =IFERROR((P73/O73)-1,0) -> 0
A74: Total Liabilities | I74: 25040 | J74: 23527 | K74: 23680 | L74: =SUM(L73+L66) -> 23548.937 | M74: =SUM(M73+M66) -> 22978.587 | N74: =SUM(N73+N66) -> 22635.671 | O74: =SUM(O73+O66) -> 22452.007 | P74: =SUM(P73+P66) -> 23453.957 | R74: =IFERROR((K74/J74)-1,0) -> 0.0065031666 | S74: =IFERROR((L74/K74)-1,0) -> -0.0055347428 | T74: =IFERROR((M74/L74)-1,0) -> -0.024219799 | U74: =IFERROR((N74/M74)-1,0) -> -0.014923275 | V74: =IFERROR((O74/N74)-1,0) -> -0.0081139289 | W74: =IFERROR((P74/O74)-1,0) -> 0.044626316
A76: Shareholders' equity:
A77: Class A convertible — 305 and 305 shares outstanding | I77: 0 | J77: 0 | K77: 0 | L77: 0 | M77: 0 | N77: 0 | O77: 0 | P77: 0 | R77: =IFERROR((K77/J77)-1,0) -> 0 | S77: =IFERROR((L77/K77)-1,0) -> 0 | T77: =IFERROR((M77/L77)-1,0) -> 0 | U77: =IFERROR((N77/M77)-1,0) -> 0 | V77: =IFERROR((O77/N77)-1,0) -> 0 | W77: =IFERROR((P77/O77)-1,0) -> 0
A78: Class B — 1,266 and 1,273 shares outstanding | F78: Held Flat for forecast | I78: 3 | J78: 3 | K78: 3 | L78: 3 | M78: 3 | N78: 3 | O78: 3 | P78: 3 | R78: =IFERROR((K78/J78)-1,0) -> 0 | S78: =IFERROR((L78/K78)-1,0) -> 0 | T78: =IFERROR((M78/L78)-1,0) -> 0 | U78: =IFERROR((N78/M78)-1,0) -> 0 | V78: =IFERROR((O78/N78)-1,0) -> 0 | W78: =IFERROR((P78/O78)-1,0) -> 0
A79: Capital in excess of stated value | F79: Held Flat for forecast | I79: 11484 | J79: 12412 | K79: 13409 | L79: 13409 | M79: 13409 | N79: 13409 | O79: 13409 | P79: 13409 | R79: =IFERROR((K79/J79)-1,0) -> 0.080325491 | S79: =IFERROR((L79/K79)-1,0) -> 0 | T79: =IFERROR((M79/L79)-1,0) -> 0 | U79: =IFERROR((N79/M79)-1,0) -> 0 | V79: =IFERROR((O79/N79)-1,0) -> 0 | W79: =IFERROR((P79/O79)-1,0) -> 0
A80: Accumulated other comprehensive income | F80: Held Flat for forecast | I80: 318 | J80: 231 | K80: 53 | L80: 53 | M80: 53 | N80: 53 | O80: 53 | P80: 53 | R80: =IFERROR((K80/J80)-1,0) -> -0.77056277 | S80: =IFERROR((L80/K80)-1,0) -> 0 | T80: =IFERROR((M80/L80)-1,0) -> 0 | U80: =IFERROR((N80/M80)-1,0) -> 0 | V80: =IFERROR((O80/N80)-1,0) -> 0 | W80: =IFERROR((P80/O80)-1,0) -> 0
A81: Retained earnings | F81: Previous Period + Net Income- Depriciation (See note) | I81: 3476 | J81: 1358 | K81: 965 | L81: =K81+L27-(3683) -> 2573.5204 | M81: =L81+M27-4355 -> 3609.2583 | N81: =M81+N27-4519 -> 4683.3996 | O81: =N81+O27-4641 -> 5898.6656 | P81: =O81+P27-4784 -> 7302.4684 | R81: =IFERROR((K81/J81)-1,0) -> -0.28939617 | S81: =IFERROR((L81/K81)-1,0) -> 1.6668606 | T81: =IFERROR((M81/L81)-1,0) -> 0.40245954 | U81: =IFERROR((N81/M81)-1,0) -> 0.29760723 | V81: =IFERROR((O81/N81)-1,0) -> 0.25948371 | W81: =IFERROR((P81/O81)-1,0) -> 0.23798652
A83: Total shareholders' equity | I83: 15281 | J83: 14004 | K83: 14430 | L83: =SUM(L77:L82) -> 16038.52 | M83: =SUM(M77:M82) -> 17074.258 | N83: =SUM(N77:N82) -> 18148.4 | O83: =SUM(O77:O82) -> 19363.666 | P83: =SUM(P77:P82) -> 20767.468 | R83: =IFERROR((K83/J83)-1,0) -> 0.03041988 | S83: =IFERROR((L83/K83)-1,0) -> 0.11147058 | T83: =IFERROR((M83/L83)-1,0) -> 0.064578142 | U83: =IFERROR((N83/M83)-1,0) -> 0.062909987 | V83: =IFERROR((O83/N83)-1,0) -> 0.066962705 | W83: =IFERROR((P83/O83)-1,0) -> 0.072496753
A85: Total Liabilities and Shareholders' Equities | I85: 40321 | J85: 37531 | K85: 38110 | L85: =L83+L74 -> 39587.458 | M85: =M83+M74 -> 40052.845 | N85: =N83+N74 -> 40784.071 | O85: =O83+O74 -> 41815.672 | P85: =P83+P74 -> 44221.426 | R85: =IFERROR((K85/J85)-1,0) -> 0.015427247 | S85: =IFERROR((L85/K85)-1,0) -> 0.038768243 | T85: =IFERROR((M85/L85)-1,0) -> 0.011755928 | U85: =IFERROR((N85/M85)-1,0) -> 0.018256521 | V85: =IFERROR((O85/N85)-1,0) -> 0.025294231 | W85: =IFERROR((P85/O85)-1,0) -> 0.057532334
A86: Error Check | I86: =ROUND(I55-I74-I83,0) -> 0 | J86: =ROUND(J55-J74-J83,0) -> 0 | K86: =ROUND(K55-K74-K83,0) -> 0 | L86: =ROUND(L55-L74-L83,0) -> 0 | M86: =ROUND(M55-M74-M83,0) -> 0 | N86: =ROUND(N55-N74-N83,0) -> 0 | O86: =ROUND(O55-O74-O83,0) -> 0 | P86: =ROUND(P55-P74-P83,0) -> 0
A88: Statement of Cash Flows
A89: Cash from operations:
A90: Net income | F90: From income statement | I90: =I23 -> 6046 | J90: =J23 -> 5070 | K90: =K23 -> 5700 | L90: =L23 -> 5291.5204 | M90: =M23 -> 5390.7378 | N90: =N23 -> 5593.1414 | O90: =O23 -> 5856.2659 | P90: =P23 -> 6187.8029
A91: Depreciation | F91: From income statement | I91: =I30 -> 717 | J91: =J30 -> 703 | K91: =K30 -> 796 | L91: =L30 -> 856.42857 | M91: =M30 -> 916.85714 | N91: =N30 -> 977.28571 | O91: =O30 -> 1037.7143 | P91: =P30 -> 1098.1429
A92: Deferred income taxes | F92: Held Flat for forecast | I92: -650 | J92: -117 | K92: -497 | L92: =K92 -> -497 | M92: =L92 -> -497 | N92: =M92 -> -497 | O92: =N92 -> -497 | P92: =O92 -> -497
A93: Stock-based compensation | F93: Held Flat for forecast | I93: 638 | J93: 755 | K93: 804 | L93: =K93 -> 804 | M93: =L93 -> 804 | N93: =M93 -> 804 | O93: =N93 -> 804 | P93: =O93 -> 804
A94: Amortization | F94: From income statement | I94: {=I31:K31} -> 123 | J94: 156 | K94: 48 | L94: =L31 -> 48 | M94: =M31 -> 48 | N94: =N31 -> 48 | O94: =O31 -> 48 | P94: =P31 -> 48
A95: Net foreign currency adjustments | F95: Held Flat for forecast | I95: -26 | J95: -213 | K95: -138 | L95: -138 | M95: -138 | N95: -138 | O95: -138 | P95: -138
A97: Changes in certain working capital components and other assets and liabilities:
A98: Change in Accounts Receivable | F98: Previous Period - Current Period | I98: -504 | J98: 489 | K98: -329 | L98: =K41-L41 -> 42.936685 | M98: =L41-M41 -> -87.681266 | N98: =M41-N41 -> -178.86978 | O98: =N41-O41 -> -232.53072 | P98: =O41-P41 -> -292.9887
A99: Change in Inventory | F99: Previous Period - Current Period | I99: -1676 | J99: -133 | K99: 908 | L99: =K42-L42 -> -904.76553 | M99: =L42-M42 -> -168.47531 | N99: =M42-N42 -> -343.68963 | O99: =N42-O42 -> -446.79652 | P99: =O42-P42 -> -562.96362
A100: Change in Prepaid Expenses | F100: Previous Period - Current Period | I100: -845 | J100: -644 | K100: -260 | L100: =K43-L43 -> -210.7524 | M100: =L43-M43 -> -41.295048 | N100: =M43-N43 -> -84.241898 | O100: =N43-O43 -> -109.51447 | P100: =O43-P43 -> -137.98823
A101: Change in Accounts Payable | F101: Current Period - Previous Period | I101: 1365 | J101: -225 | K101: 397 | L101: =L61-K61 -> 171.88237 | M101: =M61-L61 -> 60.457647 | N101: =N61-M61 -> 123.3336 | O101: =O61-N61 -> 160.33368 | P101: =P61-O61 -> 202.02044
A103: Total Cash from Operations | I103: 5188 | J103: 5841 | K103: 7429 | L103: =SUM(L90:L102) -> 5464.2501 | M103: =SUM(M90:M102) -> 6287.601 | N103: =SUM(N90:N102) -> 6303.9594 | O103: =SUM(O90:O102) -> 6482.4722 | P103: =SUM(P90:P102) -> 6711.0256
A105: Cash from Investing
A106: Purchases of short-term investments | F106: Held Flat for forecast | I106: -12913 | J106: -6059 | K106: -4767 | L106: -4767 | M106: -4767 | N106: -4767 | O106: -4767 | P106: -4767
A107: Maturities of short-term investments | F107: Held Flat for forecast | I107: 8199 | J107: 3356 | K107: 2269 | L107: 2269 | M107: 2269 | N107: 2269 | O107: 2269 | P107: 2269
A108: Sales of short-term investments | F108: Held Flat for forecast | I108: 3967 | J108: 4184 | K108: 4219 | L108: 4219 | M108: 4219 | N108: 4219 | O108: 4219 | P108: 4219
A109: Additions to property, plant and equipment | F109: Previous Period - Current Period - Depreciation | I109: -758 | J109: -969 | K109: -812 | L109: =K48-L48-L30 -> -846 | M109: =L48-M48-M30 -> -846 | N109: =M48-N48-N30 -> -846 | O109: =N48-O48-O30 -> -846 | P109: =O48-P48-P30 -> -846
A110: Other investing activities | F110: Held Flat for forecast | I110: -19 | J110: 52 | K110: -15 | L110: -15 | M110: -15 | N110: -15 | O110: -15 | P110: -15
A112: Total Cash from Investing | I112: -1524 | J112: 564 | K112: 894 | L112: =SUM(L106:L111) -> 860 | M112: =SUM(M106:M111) -> 860 | N112: =SUM(N106:N111) -> 860 | O112: =SUM(O106:O111) -> 860 | P112: =SUM(P106:P111) -> 860
A114: Cash from Financing
A115: Change in Notes Payable, net | F115: Held Flat for forecast | I115: 15 | J115: -4 | K115: 0 | L115: 0 | M115: 0 | N115: 0 | O115: 0 | P115: 0
A116: Repayment of borrowings | F116: See Maturity Schedule | I116: 0 | J116: -500 | K116: 0 | L116: {=K196:O196} -> 0 | M116: -1000 | N116: -1000 | O116: -1000 | P116: 0
A117: Proceeds from exercise of stock options and other stock issuances | F117: Held Flat for forecast | I117: 1151 | J117: 651 | K117: 667 | L117: 667 | M117: 667 | N117: 667 | O117: 667 | P117: 667
A118: Repurchase of common stock | F118: Held Flat for forecast | I118: -4014 | J118: -5480 | K118: -4250 | L118: -4250 | M118: -4250 | N118: -4250 | O118: -4250 | P118: -4250
A119: Dividends — common and preferred | F119: Held Flat for forecast | I119: -1837 | J119: -2012 | K119: -2169 | L119: -2169 | M119: -2169 | N119: -2169 | O119: -2169 | P119: -2169
A120: Other financing activities | F120: Held Flat for forecast | I120: -151 | J120: -102 | K120: -136 | L120: -136 | M120: -136 | N120: -136 | O120: -136 | P120: -136
A122: Total Cash from Financing | I122: -4836 | J122: -7447 | K122: -5888 | L122: =SUM(L115:L121) -> -5888 | M122: =SUM(M115:M121) -> -6888 | N122: =SUM(N115:N121) -> -6888 | O122: =SUM(O115:O121) -> -6888 | P122: =SUM(P115:P121) -> -5888
...

Sheet Control Panel
B2: Error Checking
B4: =SUM(B6:B13) -> 0 | C4: Master Error Check Cell
B6: =SUM(Sheet1!I86:Q86) -> 0 | C6: Balance sheet doesn't balance
B7: =SUM(Sheet1!I128:Q128) -> 0 | C7: Statement of Cash Flows doesn't match the Balance Sheet
B8: =SUM(Sheet1!I151:P151) -> 0 | C8: Tax Accrual schedule doesn't match the Balance Sheet
B9: =SUM(Sheet1!I159:P159) -> 0 | C9: PP&E Schedule doesn't match Balance Sheet
B10: =SUM(Sheet1!I165:P165) -> 0 | C10: CapEx Forecast doesn't match Statement of Cash Flows
B11: =SUM(Sheet1!I178:P178) -> 0 | C11: Depriciation Schedule doesn't match Balance Sheet
B12: =SUM(Sheet1!K186:P186) -> 0 | C12: Term Debt doesn't match Balance Sheet
B13: =SUM(Sheet1!K198:P198) -> 0 | C13: Maturity Schedule doesn't match Term Debt
C15: Put all errors above this line
B17: Formatting Guide
B18: What it looks like | C18: What it means
B19: 1000 | C19: Blue font, no shading = hardcoded actual
B20: 1000 | C20: Black font, no shading = formula
C21: Bright yellow shading = work in progress
B22: 1000 | C22: Red font, no shading = error checking cell
C23: Gray shading = deliberately left blank
B24: 1000 | C24: Blue font, light yellow shading = input or assumption
B25: 1000 | C25: Green font, no shading = info comes from another tab or workbook
B26: 1000 | C26: Orange shading = unique formula or cell
